Workbook

Sheet CTR Benchmark
A1: Expected organic CTR by average position
A2: Published industry averages for informational queries. These are the yardstick the other sheets measure against. Replace them with your own site's averages once you have three months of data — a site's real curve is usually a few points off the industry one.
A4: Position band | B4: Lower bound | C4: Expected CTR
A7: 1 | B7: 1 | C7: 0.276
A8: 2 | B8: 2 | C8: 0.158
A9: 3 | B9: 3 | C9: 0.11
A10: 4 | B10: 4 | C10: 0.084
A11: 5 | B11: 5 | C11: 0.063
A12: 6 | B12: 6 | C12: 0.049
A13: 7 | B13: 7 | C13: 0.039
A14: 8 | B14: 8 | C14: 0.033
A15: 9 | B15: 9 | C15: 0.027
A16: 10 | B16: 10 | C16: 0.024
A17: 11–15 | B17: 11 | C17: 0.018
A18: 16–20 | B18: 16 | C18: 0.012
A19: 21+ | B19: 21 | C19: 0.006

Sheet Query Analysis
A1: QUERY-LEVEL ANALYSIS. Replace the yellow cells with your own export: Search Console > Performance > Queries > Export. The sample rows below are illustrative placeholders so the model works before your data arrives — they are not measured results. Red in the CTR gap column means the query earns fewer clicks than its ranking position should deliver, which is a title and snippet problem rather than a ranking problem.
A3: Query | B3: Clicks | C3: Impressions | D3: CTR | E3: Avg position | F3: Benchmark CTR | G3: CTR gap | H3: Opportunity (clicks)
A6: what is sip in mutual fund | B6: 38 | C6: 1560 | D6: =IF(C6=0,0,B6/C6) -> 0.024358974 | E6: 6.1 | F6: =IF(E6<1,"",LOOKUP(E6,'CTR Benchmark'!$B$7:$B$19,'CTR Benchmark'!$C$7:$C$19)) -> 0.049 | G6: =IF(F6="","",D6-F6) -> -0.024641026 | H6: =IF(G6="",0,ROUND(MAX(0,-G6)*C6,0)) -> 38
A7: old vs new tax regime which is better | B7: 26 | C7: 1340 | D7: =IF(C7=0,0,B7/C7) -> 0.019402985 | E7: 7.4 | F7: =IF(E7<1,"",LOOKUP(E7,'CTR Benchmark'!$B$7:$B$19,'CTR Benchmark'!$C$7:$C$19)) -> 0.039 | G7: =IF(F7="","",D7-F7) -> -0.019597015 | H7: =IF(G7="",0,ROUND(MAX(0,-G7)*C7,0)) -> 26
A8: how to improve cibil score | B8: 14 | C8: 1190 | D8: =IF(C8=0,0,B8/C8) -> 0.011764706 | E8: 9.2 | F8: =IF(E8<1,"",LOOKUP(E8,'CTR Benchmark'!$B$7:$B$19,'CTR Benchmark'!$C$7:$C$19)) -> 0.027 | G8: =IF(F8="","",D8-F8) -> -0.015235294 | H8: =IF(G8="",0,ROUND(MAX(0,-G8)*C8,0)) -> 18
A9: section 80c deduction list | B9: 22 | C9: 870 | D9: =IF(C9=0,0,B9/C9) -> 0.025287356 | E9: 5.8 | F9: =IF(E9<1,"",LOOKUP(E9,'CTR Benchmark'!$B$7:$B$19,'CTR Benchmark'!$C$7:$C$19)) -> 0.063 | G9: =IF(F9="","",D9-F9) -> -0.037712644 | H9: =IF(G9="",0,ROUND(MAX(0,-G9)*C9,0)) -> 33
A10: what is epf and how it works | B10: 17 | C10: 760 | D10: =IF(C10=0,0,B10/C10) -> 0.022368421 | E10: 6.9 | F10: =IF(E10<1,"",LOOKUP(E10,'CTR Benchmark'!$B$7:$B$19,'CTR Benchmark'!$C$7:$C$19)) -> 0.049 | G10: =IF(F10="","",D10-F10) -> -0.026631579 | H10: =IF(G10="",0,ROUND(MAX(0,-G10)*C10,0)) -> 20
A11: how much emergency fund india | B11: 12 | C11: 480 | D11: =IF(C11=0,0,B11/C11) -> 0.025 | E11: 5.1 | F11: =IF(E11<1,"",LOOKUP(E11,'CTR Benchmark'!$B$7:$B$19,'CTR Benchmark'!$C$7:$C$19)) -> 0.063 | G11: =IF(F11="","",D11-F11) -> -0.038 | H11: =IF(G11="",0,ROUND(MAX(0,-G11)*C11,0)) -> 18
A12: what to do with first salary | B12: 19 | C12: 540 | D12: =IF(C12=0,0,B12/C12) -> 0.035185185 | E12: 4.6 | F12: =IF(E12<1,"",LOOKUP(E12,'CTR Benchmark'!$B$7:$B$19,'CTR Benchmark'!$C$7:$C$19)) -> 0.084 | G12: =IF(F12="","",D12-F12) -> -0.048814815 | H12: =IF(G12="",0,ROUND(MAX(0,-G12)*C12,0)) -> 26
A13: term insurance vs endowment plan | B13: 9 | C13: 410 | D13: =IF(C13=0,0,B13/C13) -> 0.02195122 | E13: 8.3 | F13: =IF(E13<1,"",LOOKUP(E13,'CTR Benchmark'!$B$7:$B$19,'CTR Benchmark'!$C$7:$C$19)) -> 0.033 | G13: =IF(F13="","",D13-F13) -> -0.01104878 | H13: =IF(G13="",0,ROUND(MAX(0,-G13)*C13,0)) -> 5
A14: mutual fund vs fixed deposit | B14: 11 | C14: 630 | D14: =IF(C14=0,0,B14/C14) -> 0.017460317 | E14: 7.7 | F14: =IF(E14<1,"",LOOKUP(E14,'CTR Benchmark'!$B$7:$B$19,'CTR Benchmark'!$C$7:$C$19)) -> 0.039 | G14: =IF(F14="","",D14-F14) -> -0.021539683 | H14: =IF(G14="",0,ROUND(MAX(0,-G14)*C14,0)) -> 14
A15: ppf account benefits | B15: 5 | C15: 350 | D15: =IF(C15=0,0,B15/C15) -> 0.014285714 | E15: 13.8 | F15: =IF(E15<1,"",LOOKUP(E15,'CTR Benchmark'!$B$7:$B$19,'CTR Benchmark'!$C$7:$C$19)) -> 0.018 | G15: =IF(F15="","",D15-F15) -> -0.0037142857 | H15: =IF(G15="",0,ROUND(MAX(0,-G15)*C15,0)) -> 1
A16: what is index fund india | B16: 8 | C16: 460 | D16: =IF(C16=0,0,B16/C16) -> 0.017391304 | E16: 9.9 | F16: =IF(E16<1,"",LOOKUP(E16,'CTR Benchmark'!$B$7:$B$19,'CTR Benchmark'!$C$7:$C$19)) -> 0.027 | G16: =IF(F16="","",D16-F16) -> -0.0096086957 | H16: =IF(G16="",0,ROUND(MAX(0,-G16)*C16,0)) -> 4
A17: nps scheme explained | B17: 4 | C17: 280 | D17: =IF(C17=0,0,B17/C17) -> 0.014285714 | E17: 15.4 | F17: =IF(E17<1,"",LOOKUP(E17,'CTR Benchmark'!$B$7:$B$19,'CTR Benchmark'!$C$7:$C$19)) -> 0.018 | G17: =IF(F17="","",D17-F17) -> -0.0037142857 | H17: =IF(G17="",0,ROUND(MAX(0,-G17)*C17,0)) -> 1
... A20: income tax basics for salaried india | B20: 6 | C20: 300 | D20: =IF(C20=0,0,B20/C20) -> 0.02 | E20: 11.9 | F20: =IF(E20<1,"",LOOKUP(E20,'CTR Benchmark'!$B$7:$B$19,'CTR Benchmark'!$C$7:$C$19)) -> 0.018 | G20: =IF(F20="","",D20-F20) -> 0.002 | H20: =IF(G20="",0,ROUND(MAX(0,-G20)*C20,0)) -> 0
A21: Total | B21: =SUM(B6:B20) -> 208 | C21: =SUM(C6:C20) -> 9880 | D21: =IF(C21=0,0,B21/C21) -> 0.021052632 | H21: =SUM(H6:H20) -> 214

Sheet Page Analysis
A1: PAGE-LEVEL ANALYSIS. Search Console > Performance > Pages > Export. Same method as the query sheet. Sort by the Opportunity column to decide which page to rewrite first: it converts the CTR gap into the number of clicks a better title and meta description could realistically recover.
A3: Page URL | B3: Clicks | C3: Impressions | D3: CTR | E3: Avg position | F3: Benchmark CTR | G3: CTR gap | H3: Opportunity (clicks)
A6: /what-is-sip/ | B6: 44 | C6: 1820 | D6: =IF(C6=0,0,B6/C6) -> 0.024175824 | E6: 6.2 | F6: =IF(E6<1,"",LOOKUP(E6,'CTR Benchmark'!$B$7:$B$19,'CTR Benchmark'!$C$7:$C$19)) -> 0.049 | G6: =IF(F6="","",D6-F6) -> -0.024824176 | H6: =IF(G6="",0,ROUND(MAX(0,-G6)*C6,0)) -> 45
A7: /old-vs-new-tax-regime/ | B7: 29 | C7: 1490 | D7: =IF(C7=0,0,B7/C7) -> 0.019463087 | E7: 7.3 | F7: =IF(E7<1,"",LOOKUP(E7,'CTR Benchmark'!$B$7:$B$19,'CTR Benchmark'!$C$7:$C$19)) -> 0.039 | G7: =IF(F7="","",D7-F7) -> -0.019536913 | H7: =IF(G7="",0,ROUND(MAX(0,-G7)*C7,0)) -> 29
A8: /credit-score/ | B8: 16 | C8: 1240 | D8: =IF(C8=0,0,B8/C8) -> 0.012903226 | E8: 9 | F8: =IF(E8<1,"",LOOKUP(E8,'CTR Benchmark'!$B$7:$B$19,'CTR Benchmark'!$C$7:$C$19)) -> 0.027 | G8: =IF(F8="","",D8-F8) -> -0.014096774 | H8: =IF(G8="",0,ROUND(MAX(0,-G8)*C8,0)) -> 17
A9: /section-80c/ | B9: 24 | C9: 910 | D9: =IF(C9=0,0,B9/C9) -> 0.026373626 | E9: 5.7 | F9: =IF(E9<1,"",LOOKUP(E9,'CTR Benchmark'!$B$7:$B$19,'CTR Benchmark'!$C$7:$C$19)) -> 0.063 | G9: =IF(F9="","",D9-F9) -> -0.036626374 | H9: =IF(G9="",0,ROUND(MAX(0,-G9)*C9,0)) -> 33
A10: /epf-explained/ | B10: 18 | C10: 800 | D10: =IF(C10=0,0,B10/C10) -> 0.0225 | E10: 6.8 | F10: =IF(E10<1,"",LOOKUP(E10,'CTR Benchmark'!$B$7:$B$19,'CTR Benchmark'!$C$7:$C$19)) -> 0.049 | G10: =IF(F10="","",D10-F10) -> -0.0265 | H10: =IF(G10="",0,ROUND(MAX(0,-G10)*C10,0)) -> 21
A11: /first-salary/ | B11: 21 | C11: 590 | D11: =IF(C11=0,0,B11/C11) -> 0.03559322 | E11: 4.5 | F11: =IF(E11<1,"",LOOKUP(E11,'CTR Benchmark'!$B$7:$B$19,'CTR Benchmark'!$C$7:$C$19)) -> 0.084 | G11: =IF(F11="","",D11-F11) -> -0.04840678 | H11: =IF(G11="",0,ROUND(MAX(0,-G11)*C11,0)) -> 29
A12: /emergency-fund/ | B12: 13 | C12: 510 | D12: =IF(C12=0,0,B12/C12) -> 0.025490196 | E12: 5.2 | F12: =IF(E12<1,"",LOOKUP(E12,'CTR Benchmark'!$B$7:$B$19,'CTR Benchmark'!$C$7:$C$19)) -> 0.063 | G12: =IF(F12="","",D12-F12) -> -0.037509804 | H12: =IF(G12="",0,ROUND(MAX(0,-G12)*C12,0)) -> 19
A13: /mutual-fund-vs-fd/ | B13: 12 | C13: 670 | D13: =IF(C13=0,0,B13/C13) -> 0.017910448 | E13: 7.6 | F13: =IF(E13<1,"",LOOKUP(E13,'CTR Benchmark'!$B$7:$B$19,'CTR Benchmark'!$C$7:$C$19)) -> 0.039 | G13: =IF(F13="","",D13-F13) -> -0.021089552 | H13: =IF(G13="",0,ROUND(MAX(0,-G13)*C13,0)) -> 14
A14: /compounding/ | B14: 11 | C14: 420 | D14: =IF(C14=0,0,B14/C14) -> 0.026190476 | E14: 6.3 | F14: =IF(E14<1,"",LOOKUP(E14,'CTR Benchmark'!$B$7:$B$19,'CTR Benchmark'!$C$7:$C$19)) -> 0.049 | G14: =IF(F14="","",D14-F14) -> -0.022809524 | H14: =IF(G14="",0,ROUND(MAX(0,-G14)*C14,0)) -> 10
A15: /index-funds/ | B15: 9 | C15: 490 | D15: =IF(C15=0,0,B15/C15) -> 0.018367347 | E15: 9.7 | F15: =IF(E15<1,"",LOOKUP(E15,'CTR Benchmark'!$B$7:$B$19,'CTR Benchmark'!$C$7:$C$19)) -> 0.027 | G15: =IF(F15="","",D15-F15) -> -0.0086326531 | H15: =IF(G15="",0,ROUND(MAX(0,-G15)*C15,0)) -> 4
A16: /term-insurance/ | B16: 10 | C16: 440 | D16: =IF(C16=0,0,B16/C16) -> 0.022727273 | E16: 8.1 | F16: =IF(E16<1,"",LOOKUP(E16,'CTR Benchmark'!$B$7:$B$19,'CTR Benchmark'!$C$7:$C$19)) -> 0.033 | G16: =IF(F16="","",D16-F16) -> -0.010272727 | H16: =IF(G16="",0,ROUND(MAX(0,-G16)*C16,0)) -> 5
A17: /health-insurance-basics/ | B17: 8 | C17: 350 | D17: =IF(C17=0,0,B17/C17) -> 0.022857143 | E17: 10.4 | F17: =IF(E17<1,"",LOOKUP(E17,'CTR Benchmark'!$B$7:$B$19,'CTR Benchmark'!$C$7:$C$19)) -> 0.024 | G17: =IF(F17="","",D17-F17) -> -0.0011428571 | H17: =IF(G17="",0,ROUND(MAX(0,-G17)*C17,0)) -> 0
... A23: /ppf-explained/ | B23: 0 | C23: 0 | D23: =IF(C23=0,0,B23/C23) -> 0 | E23: 0 | F23: =IF(E23<1,"",LOOKUP(E23,'CTR Benchmark'!$B$7:$B$19,'CTR Benchmark'!$C$7:$C$19)) | G23: =IF(F23="","",D23-F23) | H23: =IF(G23="",0,ROUND(MAX(0,-G23)*C23,0)) -> 0
A24: Total | B24: =SUM(B6:B23) -> 242 | C24: =SUM(C6:C23) -> 10910 | D24: =IF(C24=0,0,B24/C24) -> 0.022181485 | H24: =SUM(H6:H23) -> 229

Sheet URL Inspection Log
A1: Run every URL through Search Console > URL Inspection and record the result. The two rows showing 'Discovered - currently not indexed' are the pages orphaned in v1: nothing on the site links to them, and without a sitemap Google has no reliable route to them.
A3: URL | B3: Indexed? | C3: Coverage state | D3: Crawled as | E3: Last crawl | F3: Action taken
A6: / | B6: Yes | C6: Submitted and indexed | D6: Smartphone | F6: None needed
A7: /what-is-sip/ | B7: Yes | C7: Submitted and indexed | D7: Smartphone | F7: Title rewritten
A8: /old-vs-new-tax-regime/ | B8: Yes | C8: Submitted and indexed | D8: Smartphone | F8: Title rewritten
A9: /credit-score/ | B9: Yes | C9: Submitted and indexed | D9: Smartphone | F9: Title rewritten
A10: /section-80c/ | B10: Yes | C10: Submitted and indexed | D10: Smartphone | F10: Meta description added
A11: /epf-explained/ | B11: Yes | C11: Submitted and indexed | D11: Smartphone | F11: Meta description added
A12: /emergency-fund/ | B12: Yes | C12: Submitted and indexed | D12: Smartphone | F12: Meta description added
A13: /first-salary/ | B13: Yes | C13: Submitted and indexed | D13: Smartphone | F13: None needed
A14: /compounding/ | B14: Yes | C14: Submitted and indexed | D14: Smartphone | F14: Meta description added
A15: /index-funds/ | B15: Yes | C15: Submitted and indexed | D15: Smartphone | F15: Title rewritten
A16: /mutual-fund-vs-fd/ | B16: Yes | C16: Submitted and indexed | D16: Smartphone | F16: Meta description added
A17: /term-insurance/ | B17: Yes | C17: Submitted and indexed | D17: Smartphone | F17: Meta description added
... A25: /budgeting-guide/ | B25: No | C25: Not found (404) | D25: - | F25: Broken internal link removed in v2

Sheet Optimisation Tracker
A1: Every change made in Phase 2, with the metric it was meant to move. Record the 28-day figures before the change and 28 days after, so each edit can be judged individually rather than as one undifferentiated 'we did SEO' before-and-after.
A3: Page | B3: Change made | C3: Old title | D3: New title | E3: CTR before | F3: CTR after | G3: Change | H3: Verdict
A6: /what-is-sip/ | B6: Title rewritten to match the question asked | C6: The First Lakh | D6: What Is an SIP? Plain Explanation for Beginners | G6: =IF(OR(E6="",F6=""),"",F6-E6) | H6: =IF(G6="","awaiting data",IF(G6>0.005,"improved",IF(G6<-0.005,"worse","no clear change"))) -> awaiting data
A7: /old-vs-new-tax-regime/ | B7: Title made comparative and specific | C7: The First Lakh | D7: Old vs New Tax Regime - How to Tell Which Suits You | G7: =IF(OR(E7="",F7=""),"",F7-E7) | H7: =IF(G7="","awaiting data",IF(G7>0.005,"improved",IF(G7<-0.005,"worse","no clear change"))) -> awaiting data
A8: /credit-score/ | B8: Title rewritten around the query | C8: The First Lakh | D8: How to Improve Your CIBIL Score - What Actually Moves It | G8: =IF(OR(E8="",F8=""),"",F8-E8) | H8: =IF(G8="","awaiting data",IF(G8>0.005,"improved",IF(G8<-0.005,"worse","no clear change"))) -> awaiting data
A9: /section-80c/ | B9: Meta description added | C9: The First Lakh | D9: Section 80C Deduction List and What It Is Really Worth | G9: =IF(OR(E9="",F9=""),"",F9-E9) | H9: =IF(G9="","awaiting data",IF(G9>0.005,"improved",IF(G9<-0.005,"worse","no clear change"))) -> awaiting data
A10: /index-funds/ | B10: Title given a geographic qualifier | C10: The First Lakh | D10: Index Funds in India - How They Work | G10: =IF(OR(E10="",F10=""),"",F10-E10) | H10: =IF(G10="","awaiting data",IF(G10>0.005,"improved",IF(G10<-0.005,"worse","no clear change"))) -> awaiting data
A11: /health-insurance-basics/ | B11: Title rewritten around the audience | C11: The First Lakh | D11: Health Insurance for Young Adults in India | G11: =IF(OR(E11="",F11=""),"",F11-E11) | H11: =IF(G11="","awaiting data",IF(G11>0.005,"improved",IF(G11<-0.005,"worse","no clear change"))) -> awaiting data
A12: /nps-basics/ | B12: Orphan page linked and submitted | C12: The First Lakh | D12: NPS Explained - Tax Benefit and the Annuity Catch | G12: =IF(OR(E12="",F12=""),"",F12-E12) | H12: =IF(G12="","awaiting data",IF(G12>0.005,"improved",IF(G12<-0.005,"worse","no clear change"))) -> awaiting data
A13: /ppf-explained/ | B13: Orphan page linked and submitted | C13: The First Lakh | D13: PPF Account Benefits and the 15-Year Lock-In | G13: =IF(OR(E13="",F13=""),"",F13-E13) | H13: =IF(G13="","awaiting data",IF(G13>0.005,"improved",IF(G13<-0.005,"worse","no clear change"))) -> awaiting data
